Topsis_102103413_PIYUSH/__init__.py
Topsis_102103413_PIYUSH/__main__.py
Topsis_Piyush_102103413-1.0.1.dist-info/LICENSE
Topsis_Piyush_102103413-1.0.1.dist-info/METADATA
Topsis_Piyush_102103413-1.0.1.dist-info/WHEEL
Topsis_Piyush_102103413-1.0.1.dist-info/entry_points.txt
Topsis_Piyush_102103413-1.0.1.dist-info/top_level.txt
Topsis_Piyush_102103413-1.0.1.dist-info/RECORD
