Metadata-Version: 2.1
Name: Topsis_Piyush_102103413
Version: 1.0.1
Summary: Topsis_Piyush_102103413
Author: Piyush
Author-email: ppiyush_be21@thapar.edu
License: MIT
Classifier: License :: OSI Approved :: MIT License
Classifier: Programming Language :: Python :: 3.6
Classifier: Programming Language :: Python :: 3.7
Classifier: Programming Language :: Python :: 3.8
License-File: LICENSE
Requires-Dist: numpy
Requires-Dist: pandas
